setup.py
edem_probability/Binomialdistribution.py
edem_probability/Gaussiandistribution.py
edem_probability/Generaldistribution.py
edem_probability/__init__.py
edem_probability.egg-info/PKG-INFO
edem_probability.egg-info/SOURCES.txt
edem_probability.egg-info/dependency_links.txt
edem_probability.egg-info/not-zip-safe
edem_probability.egg-info/top_level.txt