Metadata-Version: 1.0
Name: edem-probability
Version: 0.1
Summary: Gaussian and Binomial distributions
Home-page: UNKNOWN
Author: Edem
Author-email: edemdj@gmail.com
License: UNKNOWN
Platform: UNKNOWN
